{
  "description": "SubnetLibrary is the Schema for the subnetlibraries API",
  "type": "object",
  "properties": {
    "apiVersion": {
      "description": "APIVersion defines the versioned schema of this representation of an object.\nServers should convert recognized schemas to the latest internal value, and\nmay reject unrecognized values.\nMore info: https://git.k8s.io/community/contributors/devel/sig-architecture/api-conventions.md#resources",
      "type": "string"
    },
    "kind": {
      "description": "Kind is a string value representing the REST resource this object represents.\nServers may infer this from the endpoint the client submits requests to.\nCannot be updated.\nIn CamelCase.\nMore info: https://git.k8s.io/community/contributors/devel/sig-architecture/api-conventions.md#types-kinds",
      "type": "string"
    },
    "metadata": {
      "type": "object"
    },
    "spec": {
      "description": "SubnetLibrarySpec defines the desired state of SubnetLibrary",
      "type": "object",
      "title": "Specification",
      "properties": {
        "subnet": {
          "description": "IPv4 subnet to allocate subnets from, e.g. 10.1.0.0/16",
          "type": "string",
          "title": "Subnet",
          "default": "'10.0.0.0/29'",
          "x-eda-nokia-com": {
            "ui-order-priority": 100,
            "ui-column-span": 2
          }
        },
        "subnetLength": {
          "description": "The size of the subnets to be allocated from within the parent subnet, e.g. 29 (which could allocate 10.1.0.8/29, for example).",
          "type": "integer",
          "title": "Subnet Length",
          "default": 30,
          "x-eda-nokia-com": {
            "ui-order-priority": 200,
            "ui-column-span": 1
          }
        },
        "supernet": {
          "type": "string",
          "title": "SuperNet Name",
          "x-eda-nokia-com": {
            "ui-order-priority": 300,
            "ui-column-span": 2
          }
        }
      },
      "x-eda-nokia-com": {
        "ui-conditions": [
          {
            "condition": "!(spec.nodes.length === 0 \u0026\u0026 spec.nodeSelector.length === 0)",
            "errorMsg": "Either nodes or nodeSelector must have at least one value set"
          }
        ],
        "ui-order-priority": 30
      }
    },
    "status": {
      "description": "SubnetLibraryStatus defines the observed state of SubnetLibrary",
      "type": "object",
      "title": "Status",
      "properties": {
        "nodes": {
          "description": "List of nodes this banner has been applied to",
          "type": "array",
          "title": "Nodes",
          "items": {
            "type": "string"
          }
        }
      },
      "readOnly": true,
      "x-eda-nokia-com": {
        "ui-order-priority": 20
      }
    }
  }
}